__init__.py
coverage_wrapper.py
logger.py
plugin.py
pytest_plugin.py
live_testing_coverage-0.1.0.dist-info/LICENSE
live_testing_coverage-0.1.0.dist-info/METADATA
live_testing_coverage-0.1.0.dist-info/WHEEL
live_testing_coverage-0.1.0.dist-info/entry_points.txt
live_testing_coverage-0.1.0.dist-info/top_level.txt
live_testing_coverage-0.1.0.dist-info/RECORD
