Metadata-Version: 2.1
Name: live-testing-coverage
Version: 0.1.0
Summary: Detect code covered by tests
Home-page: https://github.com/sGeeK44/python-live-testing/live-testing-coverage
Author: François Perin
Author-email: francois_perin@hotmail.fr
Maintainer: François Perin
Maintainer-email: francois_perin@hotmail.fr
License: MIT
Requires-Dist: pytest (>=3.5.0)
